dictdeeper/__init__.py
dictdeeper/core.py
dictdeeper/exceptions.py
dictdeeper/matcher.py
dictdeeper/merger.py
dictdeeper/py.typed
dictdeeper-1.2.dist-info/METADATA
dictdeeper-1.2.dist-info/WHEEL
dictdeeper-1.2.dist-info/licenses/LICENSE
dictdeeper-1.2.dist-info/RECORD
