Metadata-Version: 2.4
Name: dictdeeper
Version: 1.2
Summary: DictDeeper: Easy traversal of deeply nested dicts.
Project-URL: Homepage, https://github.com/henriquebastos/dictdeeper
Project-URL: Documentation, https://github.com/henriquebastos/dictdeeper
Project-URL: Repository, https://github.com/henriquebastos/dictdeeper
Project-URL: Issues, https://github.com/henriquebastos/dictdeeper/issues
Author-email: Henrique Bastos <henrique@bastos.net>, Matthew Scott <matt@11craft.com>
License-Expression: MIT
License-File: LICENSE
Classifier: Development Status :: 5 - Production/Stable
Classifier: Intended Audience :: Developers
Classifier: License :: OSI Approved :: MIT License
Classifier: Operating System :: OS Independent
Classifier: Programming Language :: Python :: 3
Classifier: Programming Language :: Python :: 3.8
Classifier: Programming Language :: Python :: 3.9
Classifier: Programming Language :: Python :: 3.10
Classifier: Programming Language :: Python :: 3.11
Classifier: Programming Language :: Python :: 3.12
Classifier: Programming Language :: Python :: Implementation :: CPython
Classifier: Programming Language :: Python :: Implementation :: PyPy
Classifier: Topic :: Software Development :: Libraries :: Python Modules
Requires-Python: >=3.9
Requires-Dist: arrow>=1.3.0
